topsis/__init__.py
topsis/__main__.py
topsis_akashdeep_102103243-1.0.0.dist-info/LICENSE
topsis_akashdeep_102103243-1.0.0.dist-info/MANIFEST.in
topsis_akashdeep_102103243-1.0.0.dist-info/METADATA
topsis_akashdeep_102103243-1.0.0.dist-info/WHEEL
topsis_akashdeep_102103243-1.0.0.dist-info/entry_points.txt
topsis_akashdeep_102103243-1.0.0.dist-info/top_level.txt
topsis_akashdeep_102103243-1.0.0.dist-info/RECORD
