Metadata-Version: 2.1
Name: topsis_akashdeep_102103243
Version: 1.0.0
Summary: A Python package to find TOPSIS for MCDM (Multi-Criteria Decision Analysis Method)
Author: Akashdeep Kataria
Author-email: akashdeepkataria5@gmail.com
License: MIT
Keywords: TOPSIS,MCDM
Classifier: Development Status :: 5 - Production/Stable
Classifier: Intended Audience :: Developers
Classifier: Topic :: Software Development :: Build Tools
Classifier: License :: OSI Approved :: MIT License
Classifier: Programming Language :: Python :: 3
License-File: LICENSE
Requires-Dist: numpy
Requires-Dist: pandas
Requires-Dist: logging
